LICENSE
MANIFEST.in
README.rst
setup.py
test_xerox.py
xerox/__init__.py
xerox/base.py
xerox/cli.py
xerox/core.py
xerox/darwin.py
xerox/tkinter.py
xerox/win.py
xerox/x11.py
xerox.egg-info/PKG-INFO
xerox.egg-info/SOURCES.txt
xerox.egg-info/dependency_links.txt
xerox.egg-info/entry_points.txt
xerox.egg-info/top_level.txt